README.md
setup.cfg
setup.py
datascience_utilities/__init__.py
datascience_utilities/csv_to_json.py
datascience_utilities/describe.py
datascience_utilities/exponential.py
datascience_utilities/json_to_csv.py
datascience_utilities/normal.py
datascience_utilities/plotHex.py
datascience_utilities/plotHist.py
datascience_utilities/plotXY.py
datascience_utilities/poisson.py
datascience_utilities/reservoirSampling.py
datascience_utilities/ztest.py
datascience_utilities.egg-info/PKG-INFO
datascience_utilities.egg-info/SOURCES.txt
datascience_utilities.egg-info/dependency_links.txt
datascience_utilities.egg-info/entry_points.txt
datascience_utilities.egg-info/requires.txt
datascience_utilities.egg-info/top_level.txt